rudy/__init__.py
rudy/callbacks.py
rudy/data.py
rudy/main.py
rudy-0.0.1.data/scripts/rudy
rudy-0.0.1.dist-info/METADATA
rudy-0.0.1.dist-info/WHEEL
rudy-0.0.1.dist-info/top_level.txt
rudy-0.0.1.dist-info/RECORD
